idn_data_models/__init__.py
idn_data_models/data_model.py
idn_data_models/py.typed
idn_data_models-0.1.0.dist-info/METADATA
idn_data_models-0.1.0.dist-info/WHEEL
idn_data_models-0.1.0.dist-info/RECORD
