Metadata-Version: 2.1
Name: idn-data-models
Version: 0.1.0
Summary: 
Author: Konstantinos Samaras-Tsakiris
Author-email: konstantinos@iduntechnologies.com
Requires-Python: >=3.10,<4.0
Classifier: Programming Language :: Python :: 3
Classifier: Programming Language :: Python :: 3.10
Classifier: Programming Language :: Python :: 3.11
